{
    "Student1" : {
        "name" :"Johnathon",
        "age" : "33",
        "qualification" :"BSC",
        "email":"std123@gmail.com",
        "id" : 1
    },
    "Student2" : {
        "name" : "David",
        "age" : "23",
        "qualification" : "HNC",
        "email": "david@gmail.com",
        "id" : 2
    },
    "Student3" : {
        "name" : "Emily",
        "age" : "25",
        "qualification" : "A-level",
        "email" : "emily@gmail.com",
        "id" : 3
    }
}